{
    "idSave": 721,
    "IsMusicActive": false,
    "IsSoundActive": true,
    "TotalCats": 30,
    "LevelDataYG": [
        {
            "Id": 0,
            "CatsAmount": 20,
            "CatsCoughtTotal": 20,
            "IsNeedRewardToUnlock": false,
            "IsNeedTotalCatsToUnlock": false,
            "CatsToUnlock": 0,
            "IsUnlocked": true,
            "IdOfCoughtCats": [
                2,
                15,
                13,
                12,
                16,
                18,
                7,
                11,
                6,
                1,
                10,
                9,
                17,
                8,
                3,
                19,
                0,
                4,
                14,
                5
            ]
        },
        {
            "Id": 1,
            "CatsAmount": 10,
            "CatsCoughtTotal": 10,
            "IsNeedRewardToUnlock": false,
            "IsNeedTotalCatsToUnlock": false,
            "CatsToUnlock": 0,
            "IsUnlocked": true,
            "IdOfCoughtCats": [
                3,
                8,
                2,
                1,
                6,
                9,
                5,
                0,
                7,
                4
            ]
        },
        {
            "Id": 2,
            "CatsAmount": 10,
            "CatsCoughtTotal": 0,
            "IsNeedRewardToUnlock": false,
            "IsNeedTotalCatsToUnlock": false,
            "CatsToUnlock": 0,
            "IsUnlocked": true,
            "IdOfCoughtCats": []
        },
        {
            "Id": 3,
            "CatsAmount": 20,
            "CatsCoughtTotal": 0,
            "IsNeedRewardToUnlock": false,
            "IsNeedTotalCatsToUnlock": false,
            "CatsToUnlock": 0,
            "IsUnlocked": true,
            "IdOfCoughtCats": []
        },
        {
            "Id": 4,
            "CatsAmount": 10,
            "CatsCoughtTotal": 0,
            "IsNeedRewardToUnlock": false,
            "IsNeedTotalCatsToUnlock": true,
            "CatsToUnlock": 50,
            "IsUnlocked": false,
            "IdOfCoughtCats": []
        },
        {
            "Id": 5,
            "CatsAmount": 30,
            "CatsCoughtTotal": 0,
            "IsNeedRewardToUnlock": true,
            "IsNeedTotalCatsToUnlock": false,
            "CatsToUnlock": 0,
            "IsUnlocked": true,
            "IdOfCoughtCats": []
        },
        {
            "Id": 6,
            "CatsAmount": 10,
            "CatsCoughtTotal": 0,
            "IsNeedRewardToUnlock": true,
            "IsNeedTotalCatsToUnlock": false,
            "CatsToUnlock": 0,
            "IsUnlocked": true,
            "IdOfCoughtCats": []
        },
        {
            "Id": 7,
            "CatsAmount": 30,
            "CatsCoughtTotal": 0,
            "IsNeedRewardToUnlock": false,
            "IsNeedTotalCatsToUnlock": true,
            "CatsToUnlock": 70,
            "IsUnlocked": false,
            "IdOfCoughtCats": []
        },
        {
            "Id": 8,
            "CatsAmount": 10,
            "CatsCoughtTotal": 0,
            "IsNeedRewardToUnlock": false,
            "IsNeedTotalCatsToUnlock": true,
            "CatsToUnlock": 90,
            "IsUnlocked": false,
            "IdOfCoughtCats": []
        },
        {
            "Id": 9,
            "CatsAmount": 30,
            "CatsCoughtTotal": 4,
            "IsNeedRewardToUnlock": true,
            "IsNeedTotalCatsToUnlock": false,
            "CatsToUnlock": 0,
            "IsUnlocked": true,
            "IdOfCoughtCats": [
                13,
                0,
                10,
                5
            ]
        },
        {
            "Id": 9,
            "CatsAmount": 30,
            "CatsCoughtTotal": 0,
            "IsNeedRewardToUnlock": false,
            "IsNeedTotalCatsToUnlock": true,
            "CatsToUnlock": 100,
            "IsUnlocked": false,
            "IdOfCoughtCats": []
        },
        {
            "Id": 9,
            "CatsAmount": 20,
            "CatsCoughtTotal": 0,
            "IsNeedRewardToUnlock": true,
            "IsNeedTotalCatsToUnlock": false,
            "CatsToUnlock": 0,
            "IsUnlocked": false,
            "IdOfCoughtCats": []
        },
        {
            "Id": 9,
            "CatsAmount": 20,
            "CatsCoughtTotal": 0,
            "IsNeedRewardToUnlock": true,
            "IsNeedTotalCatsToUnlock": false,
            "CatsToUnlock": 0,
            "IsUnlocked": false,
            "IdOfCoughtCats": []
        },
        {
            "Id": 9,
            "CatsAmount": 30,
            "CatsCoughtTotal": 0,
            "IsNeedRewardToUnlock": false,
            "IsNeedTotalCatsToUnlock": true,
            "CatsToUnlock": 130,
            "IsUnlocked": false,
            "IdOfCoughtCats": []
        },
        {
            "Id": 9,
            "CatsAmount": 20,
            "CatsCoughtTotal": 0,
            "IsNeedRewardToUnlock": false,
            "IsNeedTotalCatsToUnlock": true,
            "CatsToUnlock": 160,
            "IsUnlocked": false,
            "IdOfCoughtCats": []
        },
        {
            "Id": 9,
            "CatsAmount": 30,
            "CatsCoughtTotal": 0,
            "IsNeedRewardToUnlock": true,
            "IsNeedTotalCatsToUnlock": false,
            "CatsToUnlock": 0,
            "IsUnlocked": false,
            "IdOfCoughtCats": []
        },
        {
            "Id": 9,
            "CatsAmount": 15,
            "CatsCoughtTotal": 0,
            "IsNeedRewardToUnlock": false,
            "IsNeedTotalCatsToUnlock": true,
            "CatsToUnlock": 180,
            "IsUnlocked": false,
            "IdOfCoughtCats": []
        },
        {
            "Id": 17,
            "CatsAmount": 15,
            "CatsCoughtTotal": 0,
            "IsNeedRewardToUnlock": true,
            "IsNeedTotalCatsToUnlock": false,
            "CatsToUnlock": 0,
            "IsUnlocked": false,
            "IdOfCoughtCats": []
        },
        {
            "Id": 18,
            "CatsAmount": 20,
            "CatsCoughtTotal": 0,
            "IsNeedRewardToUnlock": true,
            "IsNeedTotalCatsToUnlock": false,
            "CatsToUnlock": 0,
            "IsUnlocked": false,
            "IdOfCoughtCats": []
        },
        {
            "Id": 19,
            "CatsAmount": 20,
            "CatsCoughtTotal": 0,
            "IsNeedRewardToUnlock": false,
            "IsNeedTotalCatsToUnlock": true,
            "CatsToUnlock": 380,
            "IsUnlocked": false,
            "IdOfCoughtCats": []
        }
    ]
}